textworker/__init__.py
textworker/__main__.py
textworker/generic.py
textworker/main.py
textworker/mainwindow.py
textworker/tabs.py
textworker/textwidget.py
textworker/backend/__init__.py
textworker/backend/constants.py
textworker/backend/file_operations.py
textworker/backend/get_config.py
textworker/backend/logger.py
textworker/extensions/__init__.py
textworker/extensions/autosave.py
textworker/extensions/cmd.py
textworker/extensions/multiview.py
textworker/icons/textworker.Devel.png
textworker/icons/textworker.png
textworker-1.6a1.dist-info/LICENSE
textworker-1.6a1.dist-info/METADATA
textworker-1.6a1.dist-info/WHEEL
textworker-1.6a1.dist-info/entry_points.txt
textworker-1.6a1.dist-info/top_level.txt
textworker-1.6a1.dist-info/RECORD
