Metadata-Version: 2.1
Name: textworker
Version: 1.6a1
Summary: A simple, cross-platform text editor.
Classifier: Intended Audience :: End Users/Desktop
Classifier: License :: OSI Approved :: GNU General Public License v3 (GPLv3)
Classifier: Operating System :: MacOS :: MacOS X
Classifier: Operating System :: Microsoft :: Windows
Classifier: Operating System :: POSIX
Classifier: Programming Language :: Python
Classifier: Topic :: Text Editors
Requires-Python: >=3.8
License-File: LICENSE
Requires-Dist: configparser
Requires-Dist: darkdetect
Requires-Dist: packaging
Requires-Dist: pillow
Requires-Dist: wxpython
